fosslight_util/__init__.py
fosslight_util/_get_downloadable_url.py
fosslight_util/compare_yaml.py
fosslight_util/constant.py
fosslight_util/correct.py
fosslight_util/cover.py
fosslight_util/download.py
fosslight_util/exclude.py
fosslight_util/get_pom_license.py
fosslight_util/help.py
fosslight_util/oss_item.py
fosslight_util/output_format.py
fosslight_util/parsing_yaml.py
fosslight_util/read_excel.py
fosslight_util/set_log.py
fosslight_util/spdx_licenses.py
fosslight_util/timer_thread.py
fosslight_util/write_cyclonedx.py
fosslight_util/write_excel.py
fosslight_util/write_opossum.py
fosslight_util/write_scancodejson.py
fosslight_util/write_spdx.py
fosslight_util/write_txt.py
fosslight_util/write_yaml.py
fosslight_util/resources/frequentLicenselist.json
fosslight_util/resources/frequent_license_nick_list.json
fosslight_util/resources/licenses.json
fosslight_util-2.1.39.dist-info/licenses/LICENSE
fosslight_util-2.1.39.dist-info/METADATA
fosslight_util-2.1.39.dist-info/WHEEL
fosslight_util-2.1.39.dist-info/entry_points.txt
fosslight_util-2.1.39.dist-info/top_level.txt
fosslight_util-2.1.39.dist-info/RECORD
