Metadata-Version: 2.4
Name: fosslight_util
Version: 2.1.39
Summary: FOSSLight Util
Home-page: https://github.com/fosslight/fosslight_util
Download-URL: https://github.com/fosslight/fosslight_util
Author: LG Electronics
License: Apache-2.0
Classifier: License :: OSI Approved :: Apache Software License
Classifier: Programming Language :: Python :: 3
Classifier: Programming Language :: Python :: 3.10
Classifier: Programming Language :: Python :: 3.11
Classifier: Programming Language :: Python :: 3.12
License-File: LICENSE
Requires-Dist: XlsxWriter
Requires-Dist: pandas
Requires-Dist: openpyxl
Requires-Dist: progress
Requires-Dist: PyYAML
Requires-Dist: lastversion
Requires-Dist: coloredlogs
Requires-Dist: beautifulsoup4
Requires-Dist: jsonmerge
Requires-Dist: spdx-tools==0.8.2; sys_platform == "linux"
Requires-Dist: setuptools>=65.5.1
Requires-Dist: numpy
Requires-Dist: requests
Requires-Dist: GitPython
Requires-Dist: cyclonedx-python-lib==8.5.*; sys_platform == "linux"
Requires-Dist: defusedxml
Dynamic: author
Dynamic: classifier
Dynamic: description
Dynamic: description-content-type
Dynamic: download-url
Dynamic: home-page
Dynamic: license
Dynamic: license-file
Dynamic: requires-dist
Dynamic: summary
